Workbook

Sheet FORECAST APP
A1: CHAVE | B1: CHAVE 2 | C1: GERENTE | D1: COORDENAÇÃO | E1: VENDEDOR | F1: CLIFOR | G1: CLIENTE | H1: UF | I1: EMPRESA | J1: CATEGORIA | K1: SHARE (%) | L1: FEVEREIRO 2025 | M1: MÉDIA 6M | N1: MÉDIA 3M | O1: META FEVEREIRO | P1: SELL OUT (e-Sales) | Q1: R+C | R1: ESTOQUE | S1: FORECAST 02 | T1: FORECAST 16 | U1: FORECAST 23 | V1: MARGEM/KG
A2: =J2&I2 -> LPI 25KGLACTALIS | B2: =F2&J2&I2 -> 5115621LPI 25KGLACTALIS | C2: MAURICIO | D2: JOEL | E2: DLUM | F2: 5115621 | G2: MARAJOARA INDUSTRIA DE LATICINI | H2: GO | I2: LACTALIS | J2: LPI 25KG | K2: 0 | L2: 0 | M2: -333.33333 | N2: 0 | O2: 10327.385 | P2: 0 | Q2: 0 | R2: 0 | S2: 0 | T2: 0 | U2: 0 | V2: =VLOOKUP(A2,Planilha1!B:E,4,0) -> -4.3046759
A3: =J3&I3 -> COMPOSTOITAMBÉ | B3: =F3&J3&I3 -> 5173427COMPOSTOITAMBÉ | C3: MAURICIO | D3: JOEL | E3: DUAS RODAS | F3: 5173427 | G3: DISTRIPACK DIST DE EMBALAGENS LTDA | H3: MG | I3: ITAMBÉ | J3: COMPOSTO | K3: 0 | L3: 0 | M3: 3637.5 | N3: 4000 | O3: 4825.3004 | P3: 0 | Q3: 12000 | R3: 0 | S3: 0 | T3: 12000 | U3: 0 | V3: =VLOOKUP(A3,Planilha1!B:E,4,0) -> 0.15618218
A4: =J4&I4 -> LPI 25KGITAMBÉ | B4: =F4&J4&I4 -> 5012038LPI 25KGITAMBÉ | C4: MAURICIO | D4: TATIANA NITTA | E4: TATIANA NITTA | F4: 5012038 | G4: HARALD INDUSTRIA E COMERCIO ALI | H4: SP | I4: ITAMBÉ | J4: LPI 25KG | K4: 0 | L4: 0 | M4: 4000 | N4: 8000 | O4: 0 | P4: 0 | Q4: 48000 | R4: 0 | S4: 0 | T4: 48000 | U4: 0 | V4: =VLOOKUP(A4,Planilha1!B:E,4,0) -> -1.2181928
A5: =J5&I5 -> LEITE CONDENSADOITAMBÉ | B5: =F5&J5&I5 -> 5223996LEITE CONDENSADOITAMBÉ | C5: MAURICIO | D5: JOEL | E5: DUAS RODAS | F5: 5223996 | G5: PLASTIC DISTRIBUIDORA LTDA | H5: ES | I5: ITAMBÉ | J5: LEITE CONDENSADO | K5: 0 | L5: 0 | M5: 31.995 | N5: 0 | O5: 126.99771 | P5: 0 | Q5: 129.02 | R5: 0 | S5: 0 | T5: 0 | U5: 0 | V5: =VLOOKUP(A5,Planilha1!B:E,4,0) -> 1.4766793
A6: =J6&I6 -> CREME UHTITAMBÉ | B6: =F6&J6&I6 -> 5223996CREME UHTITAMBÉ | C6: MAURICIO | D6: JOEL | E6: DUAS RODAS | F6: 5223996 | G6: PLASTIC DISTRIBUIDORA LTDA | H6: ES | I6: ITAMBÉ | J6: CREME UHT | K6: 0 | L6: 0 | M6: 0.16833333 | N6: 0 | O6: 18.999261 | P6: 0 | Q6: 32.4 | R6: 0 | S6: 0 | T6: 0 | U6: 0 | V6: =VLOOKUP(A6,Planilha1!B:E,4,0) -> 1.236254
A7: =J7&I7 -> COMPOSTOITAMBÉ | B7: =F7&J7&I7 -> 5224563COMPOSTOITAMBÉ | C7: MAURICIO | D7: JOEL | E7: DUAS RODAS | F7: 5224563 | G7: MC DAVE S INDUSTRIA DE SORVETES | H7: AM | I7: ITAMBÉ | J7: COMPOSTO | K7: 0 | L7: 0 | M7: 416.66667 | N7: 833.33333 | O7: 521.57706 | P7: 0 | Q7: 0 | R7: 0 | S7: 0 | T7: 0 | U7: 0 | V7: =VLOOKUP(A7,Planilha1!B:E,4,0) -> 0.15618218
A8: =J8&I8 -> COMPOSTOITAMBÉ | B8: =F8&J8&I8 -> 5313336COMPOSTOITAMBÉ | C8: MAURICIO | D8: JOEL | E8: DUAS RODAS | F8: 5313336 | G8: M C COMERCIO DE DOCES E | H8: AM | I8: ITAMBÉ | J8: COMPOSTO | K8: 0 | L8: 0 | M8: 333.33333 | N8: 0 | O8: 463.14903 | P8: 0 | Q8: 0 | R8: 0 | S8: 0 | T8: 0 | U8: 0 | V8: =VLOOKUP(A8,Planilha1!B:E,4,0) -> 0.15618218
A9: =J9&I9 -> COMPOSTOITAMBÉ | B9: =F9&J9&I9 -> 5319281COMPOSTOITAMBÉ | C9: MAURICIO | D9: JOEL | E9: DUAS RODAS | F9: 5319281 | G9: DISPPAN DIST DE PROD PANIFICACAO | H9: AM | I9: ITAMBÉ | J9: COMPOSTO | K9: 0 | L9: 10000 | M9: 1037.5 | N9: 0 | O9: 8114.371 | P9: 0 | Q9: 0 | R9: 0 | S9: 0 | T9: 0 | U9: 0 | V9: =VLOOKUP(A9,Planilha1!B:E,4,0) -> 0.15618218
A10: =J10&I10 -> COMPOSTOITAMBÉ | B10: =F10&J10&I10 -> 5335635COMPOSTOITAMBÉ | C10: MAURICIO | D10: JOEL | E10: DUAS RODAS | F10: 5335635 | G10: SUSANA SALES SIQUEIRA 159179698 | H10: BA | I10: ITAMBÉ | J10: COMPOSTO | K10: 0 | L10: 0 | M10: 141.66667 | N10: 0 | O10: 393.32041 | P10: 0 | Q10: 0 | R10: 0 | S10: 0 | T10: 0 | U10: 0 | V10: =VLOOKUP(A10,Planilha1!B:E,4,0) -> 0.15618218
A11: =J11&I11 -> LPD 25KGLACTALIS | B11: =F11&J11&I11 -> 5219478LPD 25KGLACTALIS | C11: MAURICIO | D11: JOEL | E11: FERREIRA MELO | F11: 5219478 | G11: YAKULT SA INDUSTRIA E COMERCIO | H11: SP | I11: LACTALIS | J11: LPD 25KG | K11: 0 | L11: 648000 | M11: 74970.833 | N11: 100000 | O11: 29872.139 | P11: 0 | Q11: 0 | R11: 0 | S11: 0 | T11: 0 | U11: 0 | V11: =VLOOKUP(A11,Planilha1!B:E,4,0) -> 5.8936291
A12: =J12&I12 -> LEITE CONDENSADOITAMBÉ | B12: =F12&J12&I12 -> 5019640LEITE CONDENSADOITAMBÉ | C12: MAURICIO | D12: JOEL | E12: HENRIQUE FERREIRA | F12: 5019640 | G12: BIG CHURROS DE PIRACICABA LTDA | H12: SP | I12: ITAMBÉ | J12: LEITE CONDENSADO | K12: 0 | L12: 0 | M12: 8.3333333 | N12: 0 | O12: 263.99525 | P12: 0 | Q12: 0 | R12: 0 | S12: 0 | T12: 0 | U12: 0 | V12: =VLOOKUP(A12,Planilha1!B:E,4,0) -> 1.4766793
A13: =J13&I13 -> DOCE DE LEITEITAMBÉ | B13: =F13&J13&I13 -> 5019640DOCE DE LEITEITAMBÉ | C13: MAURICIO | D13: JOEL | E13: HENRIQUE FERREIRA | F13: 5019640 | G13: BIG CHURROS DE PIRACICABA LTDA | H13: SP | I13: ITAMBÉ | J13: DOCE DE LEITE | K13: 0 | L13: 1590 | M13: 483.33333 | N13: 460 | O13: 394.02252 | P13: 0 | Q13: 240 | R13: 0 | S13: 0 | T13: 240 | U13: 0 | V13: =VLOOKUP(A13,Planilha1!B:E,4,0) -> 5.8210744
... A3230: =J3230&I3230 -> LEITE UHTLACTALIS | B3230: =F3230&J3230&I3230 -> 5363097LEITE UHTLACTALIS | C3230: RODRIGO | D3230: ALEXANDRO | E3230: CLIENTE FLAC | F3230: 5363097 | G3230: PDO ALIMENTOS E COME SOCIE EMPR | H3230: SP | I3230: LACTALIS | J3230: LEITE UHT | K3230: 0 | L3230: 0 | M3230: 0 | N3230: 0 | O3230: 0 | P3230: 0 | Q3230: 0 | R3230: 0 | S3230: 0 | T3230: 0 | U3230: 0 | V3230: =VLOOKUP(A3230,Planilha1!B:E,4,0) -> 0.37177548
A3231: =J3231&I3231 -> LEITE UHTLACTALIS | B3231: =F3231&J3231&I3231 -> 5363801LEITE UHTLACTALIS | C3231: #N/A | D3231: #N/A | E3231: #N/A | F3231: 5363801 | G3231: Não Atribuído | H3231: SP | I3231: LACTALIS | J3231: LEITE UHT | K3231: 0 | L3231: 0 | M3231: 0 | N3231: 0 | O3231: 0 | P3231: 0 | Q3231: 0 | R3231: 0 | S3231: 0 | T3231: 0 | U3231: 0 | V3231: =VLOOKUP(A3231,Planilha1!B:E,4,0) -> 0.37177548
A3232: =J3232&I3232 -> LPD 25KGITAMBÉ | B3232: =F3232&J3232&I3232 -> 5059695LPD 25KGITAMBÉ | C3232: MAURICIO | D3232: TATIANA NITTA | E3232: TATIANA NITTA | F3232: 5059695 | G3232: POLENGHI INDUSTRIAS ALIMS LTDA | H3232: SP | I3232: ITAMBÉ | J3232: LPD 25KG | K3232: 0 | L3232: 0 | M3232: 0 | N3232: 0 | O3232: 0 | P3232: 0 | Q3232: 0 | R3232: 0 | S3232: 0 | T3232: 0 | U3232: 0 | V3232: =VLOOKUP(A3232,Planilha1!B:E,4,0) -> 3.3372177
A3233: =J3233&I3233 -> LPD 25KGITAMBÉ | B3233: =F3233&J3233&I3233 -> 5220627LPD 25KGITAMBÉ | C3233: RODRIGO | D3233: JESSICA | E3233: LUCIANA MARTINS | F3233: 5220627 | G3233: JME RAUTA COMERCIAL DISTRIBUIDORA | H3233: RJ | I3233: ITAMBÉ | J3233: LPD 25KG | K3233: 0 | L3233: 0 | M3233: 0 | N3233: 0 | O3233: 0 | P3233: 0 | Q3233: 0 | R3233: 0 | S3233: 0 | T3233: 0 | U3233: 0 | V3233: =VLOOKUP(A3233,Planilha1!B:E,4,0) -> 3.3372177
A3234: =J3234&I3234 -> LPD 25KGITAMBÉ | B3234: =F3234&J3234&I3234 -> 5353050LPD 25KGITAMBÉ | C3234: MAURICIO | D3234: TATIANA NITTA | E3234: TATIANA NITTA | F3234: 5353050 | G3234: ALIBEY IND E COM DE ALIM E LTDA | H3234: SP | I3234: ITAMBÉ | J3234: LPD 25KG | K3234: 0 | L3234: 0 | M3234: 0 | N3234: 166.66667 | O3234: 0 | P3234: 0 | Q3234: 0 | R3234: 0 | S3234: 0 | T3234: 0 | U3234: 0 | V3234: =VLOOKUP(A3234,Planilha1!B:E,4,0) -> 3.3372177
A3235: =J3235&I3235 -> LPI 25KGITAMBÉ | B3235: =F3235&J3235&I3235 -> 5063322LPI 25KGITAMBÉ | C3235: RODRIGO | D3235: CELIO MARTINS | E3235: MARCELO SILVA | F3235: 5063322 | G3235: C D A DISTRIBUIDORA DE ALIMENTO | H3235: MG | I3235: ITAMBÉ | J3235: LPI 25KG | K3235: 0 | L3235: 0 | M3235: 0 | N3235: 166.66667 | O3235: 0 | P3235: 0 | Q3235: 0 | R3235: 0 | S3235: 0 | T3235: 0 | U3235: 0 | V3235: =VLOOKUP(A3235,Planilha1!B:E,4,0) -> -1.2181928
A3236: =J3236&I3236 -> LPI 25KGITAMBÉ | B3236: =F3236&J3236&I3236 -> 5157986LPI 25KGITAMBÉ | C3236: MAURICIO | D3236: JOEL | E3236: JOEL ELEOTÉRIO | F3236: 5157986 | G3236: INDUSTRIA E COM DE PROD ALIM GELONI | H3236: PR | I3236: ITAMBÉ | J3236: LPI 25KG | K3236: 0 | L3236: 0 | M3236: 0 | N3236: 4666.6667 | O3236: 0 | P3236: 0 | Q3236: 0 | R3236: 0 | S3236: 0 | T3236: 0 | U3236: 0 | V3236: =VLOOKUP(A3236,Planilha1!B:E,4,0) -> -1.2181928
A3237: =J3237&I3237 -> LPI 25KGITAMBÉ | B3237: =F3237&J3237&I3237 -> 5176952LPI 25KGITAMBÉ | C3237: RODRIGO | D3237: ALEXANDRO | E3237: EMMANUEL FRANCISCO | F3237: 5176952 | G3237: CLUBE DO CONFEITEIRO LTDA | H3237: SP | I3237: ITAMBÉ | J3237: LPI 25KG | K3237: 0 | L3237: 0 | M3237: 0 | N3237: 83.333333 | O3237: 0 | P3237: 0 | Q3237: 0 | R3237: 0 | S3237: 0 | T3237: 0 | U3237: 0 | V3237: =VLOOKUP(A3237,Planilha1!B:E,4,0) -> -1.2181928
A3238: =J3238&I3238 -> LPI 25KGITAMBÉ | B3238: =F3238&J3238&I3238 -> 5206787LPI 25KGITAMBÉ | C3238: PEDRO | D3238: ANA MENIQUETE | E3238: ANA MENIQUETE | F3238: 5206787 | G3238: CS FABRICACAO DE ALIMENTOS | H3238: SP | I3238: ITAMBÉ | J3238: LPI 25KG | K3238: 0 | L3238: 0 | M3238: 0 | N3238: 100 | O3238: 0 | P3238: 0 | Q3238: 0 | R3238: 0 | S3238: 0 | T3238: 0 | U3238: 0 | V3238: =VLOOKUP(A3238,Planilha1!B:E,4,0) -> -1.2181928
A3239: =J3239&I3239 -> LPI 25KGITAMBÉ | B3239: =F3239&J3239&I3239 -> 5232803LPI 25KGITAMBÉ | C3239: MAURICIO | D3239: JOEL | E3239: HENRIQUE FERREIRA | F3239: 5232803 | G3239: L GONZAGA MIX AMBIENTAL | H3239: SP | I3239: ITAMBÉ | J3239: LPI 25KG | K3239: 0 | L3239: 0 | M3239: 0 | N3239: 5000 | O3239: 0 | P3239: 0 | Q3239: 0 | R3239: 0 | S3239: 0 | T3239: 0 | U3239: 0 | V3239: =VLOOKUP(A3239,Planilha1!B:E,4,0) -> -1.2181928
A3240: =J3240&I3240 -> LPI 25KGITAMBÉ | B3240: =F3240&J3240&I3240 -> 5318875LPI 25KGITAMBÉ | C3240: RODRIGO | D3240: CELIO MARTINS | E3240: CELIO/MARANATHA | F3240: 5318875 | G3240: OESA COMERCIO E REPRESENTACOES | H3240: MG | I3240: ITAMBÉ | J3240: LPI 25KG | K3240: 0 | L3240: 0 | M3240: 0 | N3240: 8.3333333 | O3240: 0 | P3240: 0 | Q3240: 125 | R3240: 0 | S3240: 0 | T3240: 0 | U3240: 0 | V3240: =VLOOKUP(A3240,Planilha1!B:E,4,0) -> -1.2181928
A3241: =J3241&I3241 -> LPI 25KGITAMBÉ | B3241: =F3241&J3241&I3241 -> 5341743LPI 25KGITAMBÉ | C3241: MAURICIO | D3241: JOEL | E3241: JOEL ELEOTÉRIO | F3241: 5341743 | G3241: MAURO SIQUEIRA DE MOURA JUNIOR | H3241: SP | I3241: ITAMBÉ | J3241: LPI 25KG | K3241: 0 | L3241: 0 | M3241: 0 | N3241: 16666.667 | O3241: 0 | P3241: 0 | Q3241: 0 | R3241: 0 | S3241: 0 | T3241: 0 | U3241: 0 | V3241: =VLOOKUP(A3241,Planilha1!B:E,4,0) -> -1.2181928
A3242: =J3242&I3242 -> LPI 25KGITAMBÉ | B3242: =F3242&J3242&I3242 -> 5360926LPI 25KGITAMBÉ | C3242: MAURICIO | D3242: JOEL | E3242: HENRIQUE FERREIRA | F3242: 5360926 | G3242: MISTER DISTRIBUIDORA LTDA | H3242: MA | I3242: ITAMBÉ | J3242: LPI 25KG | K3242: 0 | L3242: 0 | M3242: 0 | N3242: 166.66667 | O3242: 0 | P3242: 0 | Q3242: 0 | R3242: 0 | S3242: 0 | T3242: 0 | U3242: 0 | V3242: =VLOOKUP(A3242,Planilha1!B:E,4,0) -> -1.2181928
A3243: =J3243&I3243 -> LPI 25KGLACTALIS | B3243: =F3243&J3243&I3243 -> 5010931LPI 25KGLACTALIS | C3243: MAURICIO | D3243: MARCELO | E3243: MARCELO RODRIGUES | F3243: 5010931 | G3243: SAO FRANCISCO IND DE ALIMENTOS | H3243: PR | I3243: LACTALIS | J3243: LPI 25KG | K3243: 0 | L3243: 0 | M3243: 0 | N3243: 33.333333 | O3243: 0 | P3243: 0 | Q3243: 0 | R3243: 0 | S3243: 0 | T3243: 0 | U3243: 0 | V3243: =VLOOKUP(A3243,Planilha1!B:E,4,0) -> -4.3046759
... A3729: =J3729&I3729 -> COMPOSTOITAMBÉ | B3729: =F3729&J3729&I3729 -> 5189644COMPOSTOITAMBÉ | C3729: RODRIGO | D3729: ALEXANDRO | E3729: EMMANUEL FRANCISCO | F3729: 5189644 | G3729: BOCAO COMERCIO DE DOCES LTDA | H3729: SP | I3729: ITAMBÉ | J3729: COMPOSTO | K3729: 0 | L3729: 0 | M3729: 0 | N3729: 0 | O3729: 0 | P3729: 0 | Q3729: 0 | R3729: 0 | S3729: 10 | T3729: 10 | U3729: 10 | V3729: =VLOOKUP(A3729,Planilha1!B:E,4,0) -> 0.15618218
A3730: =J3730&I3730 -> CREME UHTITAMBÉ | B3730: =F3730&J3730&I3730 -> 5105392CREME UHTITAMBÉ | C3730: #N/A | D3730: #N/A | E3730: #N/A | F3730: 5105392 | G3730: Não Atribuído | H3730: NA | I3730: ITAMBÉ | J3730: CREME UHT | K3730: 0 | L3730: 0 | M3730: 0 | N3730: 0 | O3730: 0 | P3730: 0 | Q3730: 0 | R3730: 0 | S3730: 12 | T3730: 12 | U3730: 0 | V3730: =VLOOKUP(A3730,Planilha1!B:E,4,0) -> 1.236254
A3731: =J3731&I3731 -> DOCE DE LEITEITAMBÉ | B3731: =F3731&J3731&I3731 -> 5105392DOCE DE LEITEITAMBÉ | C3731: #N/A | D3731: #N/A | E3731: #N/A | F3731: 5105392 | G3731: Não Atribuído | H3731: NA | I3731: ITAMBÉ | J3731: DOCE DE LEITE | K3731: 0 | L3731: 0 | M3731: 0 | N3731: 0 | O3731: 0 | P3731: 0 | Q3731: 0 | R3731: 0 | S3731: 20 | T3731: 20 | U3731: 0 | V3731: =VLOOKUP(A3731,Planilha1!B:E,4,0) -> 5.8210744
A3732: =J3732&I3732 -> LEITE CONDENSADOITAMBÉ | B3732: =F3732&J3732&I3732 -> 5105392LEITE CONDENSADOITAMBÉ | C3732: #N/A | D3732: #N/A | E3732: #N/A | F3732: 5105392 | G3732: Não Atribuído | H3732: NA | I3732: ITAMBÉ | J3732: LEITE CONDENSADO | K3732: 0 | L3732: 0 | M3732: 0 | N3732: 0 | O3732: 0 | P3732: 0 | Q3732: 0 | R3732: 0 | S3732: 200 | T3732: 200 | U3732: 0 | V3732: =VLOOKUP(A3732,Planilha1!B:E,4,0) -> 1.4766793
A3733: =J3733&I3733 -> LEITE CONDENSADOITAMBÉ | B3733: =F3733&J3733&I3733 -> 5335628LEITE CONDENSADOITAMBÉ | C3733: RODRIGO | D3733: CELIO MARTINS | E3733: CELIO MARTINS | F3733: 5335628 | G3733: COMERCIO E REPRESENTACOES CECOT | H3733: MG | I3733: ITAMBÉ | J3733: LEITE CONDENSADO | K3733: 0 | L3733: 0 | M3733: 0 | N3733: 0 | O3733: 0 | P3733: 0 | Q3733: 0 | R3733: 0 | S3733: 0 | T3733: 0 | U3733: 510 | V3733: =VLOOKUP(A3733,Planilha1!B:E,4,0) -> 1.4766793
A3734: =J3734&I3734 -> LEITE EM PÓITAMBÉ | B3734: =F3734&J3734&I3734 -> 5105392LEITE EM PÓITAMBÉ | C3734: #N/A | D3734: #N/A | E3734: #N/A | F3734: 5105392 | G3734: Não Atribuído | H3734: NA | I3734: ITAMBÉ | J3734: LEITE EM PÓ | K3734: 0 | L3734: 0 | M3734: 0 | N3734: 0 | O3734: 0 | P3734: 0 | Q3734: 0 | R3734: 0 | S3734: 0 | T3734: 0 | U3734: 0 | V3734: =VLOOKUP(A3734,Planilha1!B:E,4,0) -> 4.5971523
A3735: =J3735&I3735 -> LEITE UHTLACTALIS | B3735: =F3735&J3735&I3735 -> 5273270LEITE UHTLACTALIS | C3735: RODRIGO | D3735: ALEXANDRO | E3735: CLIENTE FLAC | F3735: 5273270 | G3735: AAP CASTRO E FERNANDES LTDA | H3735: SP | I3735: LACTALIS | J3735: LEITE UHT | K3735: 0 | L3735: 0 | M3735: 0 | N3735: 0 | O3735: 0 | P3735: 0 | Q3735: 0 | R3735: 0 | S3735: 0 | T3735: 0 | U3735: 0 | V3735: =VLOOKUP(A3735,Planilha1!B:E,4,0) -> 0.37177548
A3736: =J3736&I3736 -> LEITE UHTLACTALIS | B3736: =F3736&J3736&I3736 -> 5291710LEITE UHTLACTALIS | C3736: RODRIGO | D3736: ALEXANDRO | E3736: CLIENTE FLAC | F3736: 5291710 | G3736: MARQUES FABRICACAO E COMERC ALIM LT | H3736: SP | I3736: LACTALIS | J3736: LEITE UHT | K3736: 0 | L3736: 0 | M3736: 0 | N3736: 0 | O3736: 0 | P3736: 0 | Q3736: 0 | R3736: 0 | S3736: 0 | T3736: 0 | U3736: 0 | V3736: =VLOOKUP(A3736,Planilha1!B:E,4,0) -> 0.37177548
A3737: =J3737&I3737 -> LPD 25KGLACTALIS | B3737: =F3737&J3737&I3737 -> 5143169LPD 25KGLACTALIS | C3737: MAURICIO | D3737: MARCELO | E3737: MARCELO RODRIGUES | F3737: 5143169 | G3737: LATICINIOS TIROLEZ LTDA | H3737: SP | I3737: LACTALIS | J3737: LPD 25KG | K3737: 0 | L3737: 12000 | M3737: 6041.6667 | N3737: 5500 | O3737: 1767.2624 | P3737: 0 | Q3737: 0 | R3737: 0 | S3737: 0 | T3737: 0 | U3737: 0 | V3737: =VLOOKUP(A3737,Planilha1!B:E,4,0) -> 5.8936291
A3738: =J3738&I3738 -> MANTEIGA 5KGITAMBÉ | B3738: =F3738&J3738&I3738 -> 5352254MANTEIGA 5KGITAMBÉ | C3738: PEDRO | D3738: AMANDA | E3738: AMANDA CARVALHO | F3738: 5352254 | G3738: COCO BAMBU SUL PIZZARIA LTDA | H3738: CE | I3738: ITAMBÉ | J3738: MANTEIGA 5KG | K3738: 0 | L3738: 0 | M3738: 0 | N3738: 0 | O3738: 0 | P3738: 0 | Q3738: 40 | R3738: 0 | S3738: 0 | T3738: 0 | U3738: 60 | V3738: =VLOOKUP(A3738,Planilha1!B:E,4,0) -> 5.8198005
A3739: =J3739&I3739 -> MANTEIGA 5KGITAMBÉ | B3739: =F3739&J3739&I3739 -> 5352264MANTEIGA 5KGITAMBÉ | C3739: PEDRO | D3739: AMANDA | E3739: AMANDA CARVALHO | F3739: 5352264 | G3739: DOM PASTEL ALIMENTOS LTDA | H3739: CE | I3739: ITAMBÉ | J3739: MANTEIGA 5KG | K3739: 0 | L3739: 0 | M3739: 0 | N3739: 0 | O3739: 0 | P3739: 0 | Q3739: 0 | R3739: 0 | S3739: 0 | T3739: 0 | U3739: 50 | V3739: =VLOOKUP(A3739,Planilha1!B:E,4,0) -> 5.8198005
A3740: =J3740&I3740 -> MERC + AROMITAMBÉ | B3740: =F3740&J3740&I3740 -> 5008636MERC + AROMITAMBÉ | C3740: PEDRO | D3740: AMANDA | E3740: NUTRI | F3740: 5008636 | G3740: GR SERVICOS E ALIMENTACAO LTDA | H3740: RJ | I3740: ITAMBÉ | J3740: MERC + AROM | K3740: 0 | L3740: 0 | M3740: 0 | N3740: 0 | O3740: 0 | P3740: 0 | Q3740: 972 | R3740: 0 | S3740: 0 | T3740: 0 | U3740: 0 | V3740: =VLOOKUP(A3740,Planilha1!B:E,4,0) -> 1.038402
A3741: =J3741&I3741 -> LEITE EM PÓITAMBÉ | B3741: =F3741&J3741&I3741 -> 5145924LEITE EM PÓITAMBÉ | C3741: MAURICIO | D3741: JOEL | E3741: JOEL ELEOTÉRIO | F3741: 5145924 | G3741: CAFE TRES CORACOES SA | H3741: MG | I3741: ITAMBÉ | J3741: LEITE EM PÓ | K3741: 0 | L3741: 8000 | M3741: 3083.3333 | N3741: 3500 | O3741: 0 | P3741: 0 | Q3741: 0 | R3741: 0 | S3741: 0 | T3741: 0 | U3741: 0 | V3741: =VLOOKUP(A3741,Planilha1!B:E,4,0) -> 4.5971523
A3742: =J3742&I3742 -> LPD 25KGITAMBÉ | B3742: =F3742&J3742&I3742 -> 5145924LPD 25KGITAMBÉ | C3742: MAURICIO | D3742: JOEL | E3742: JOEL ELEOTÉRIO | F3742: 5145924 | G3742: CAFE TRES CORACOES SA | H3742: MG | I3742: ITAMBÉ | J3742: LPD 25KG | K3742: 0 | L3742: 24000 | M3742: 24000 | N3742: 32000 | O3742: 57686.345 | P3742: 0 | Q3742: 49000 | R3742: 0 | S3742: 0 | T3742: 72000 | U3742: 0 | V3742: =VLOOKUP(A3742,Planilha1!B:E,4,0) -> 3.3372177
A3743: =J3743&I3743 -> LPD 25KGITAMBÉ | B3743: =F3743&J3743&I3743 -> 5157826LPD 25KGITAMBÉ | C3743: MAURICIO | D3743: TATIANA NITTA | E3743: TATIANA NITTA | F3743: 5157826 | G3743: IBAC INDUSTRIA BRASILEIRA DE ALIM C | H3743: SP | I3743: ITAMBÉ | J3743: LPD 25KG | K3743: 0 | L3743: 24000 | M3743: 7891.6667 | N3743: 8000 | O3743: 3737.0249 | P3743: 0 | Q3743: 0 | R3743: 0 | S3743: 0 | T3743: 0 | U3743: 0 | V3743: =VLOOKUP(A3743,Planilha1!B:E,4,0) -> 3.3372177
A3744: =J3744&I3744 -> LEITE EM PÓITAMBÉ | B3744: =F3744&J3744&I3744 -> 5160241LEITE EM PÓITAMBÉ | C3744: MAURICIO | D3744: JOEL | E3744: JOEL ELEOTÉRIO | F3744: 5160241 | G3744: TRES CORACOES ALIMENTOS SA | H3744: RN | I3744: ITAMBÉ | J3744: LEITE EM PÓ | K3744: 0 | L3744: 3000 | M3744: 0 | N3744: 0 | O3744: 367.92597 | P3744: 0 | Q3744: 0 | R3744: 0 | S3744: 0 | T3744: 0 | U3744: 0 | V3744: =VLOOKUP(A3744,Planilha1!B:E,4,0) -> 4.5971523
A3745: =J3745&I3745 -> LPD 25KGITAMBÉ | B3745: =F3745&J3745&I3745 -> 5160241LPD 25KGITAMBÉ | C3745: MAURICIO | D3745: JOEL | E3745: JOEL ELEOTÉRIO | F3745: 5160241 | G3745: TRES CORACOES ALIMENTOS SA | H3745: RN | I3745: ITAMBÉ | J3745: LPD 25KG | K3745: 0 | L3745: 48000 | M3745: 32000 | N3745: 32000 | O3745: 19784.772 | P3745: 0 | Q3745: 24000 | R3745: 0 | S3745: 0 | T3745: 24000 | U3745: 0 | V3745: =VLOOKUP(A3745,Planilha1!B:E,4,0) -> 3.3372177
A3746: =J3746&I3746 -> LPI 25KGLACTALIS | B3746: =F3746&J3746&I3746 -> 5160918LPI 25KGLACTALIS | C3746: MAURICIO | D3746: MARCELO | E3746: MARCELO RODRIGUES | F3746: 5160918 | G3746: PECCIN S A | H3746: RS | I3746: LACTALIS | J3746: LPI 25KG | K3746: 0 | L3746: 0 | M3746: 36000 | N3746: 56000 | O3746: 18387.207 | P3746: 0 | Q3746: 0 | R3746: 0 | S3746: 0 | T3746: 0 | U3746: 0 | V3746: =VLOOKUP(A3746,Planilha1!B:E,4,0) -> -4.3046759
A3747: =J3747&I3747 -> MANTEIGA 5KGLACTALIS | B3747: =F3747&J3747&I3747 -> 5363684MANTEIGA 5KGLACTALIS | C3747: RODRIGO | D3747: ALEXANDRO | E3747: CLIENTE FLAC | F3747: 5363684 | G3747: BAKERY AND MUSIC BOUTIQUE DE PAES L | H3747: SP | I3747: LACTALIS | J3747: MANTEIGA 5KG | K3747: 0 | L3747: 0 | M3747: 0 | N3747: 0 | O3747: 0 | P3747: 0 | Q3747: 0 | R3747: 0 | S3747: 85 | T3747: 85 | U3747: 45 | V3747: =VLOOKUP(A3747,Planilha1!B:E,4,0) -> 11.476197
A3748: =J3748&I3748 -> IOGURTESLACTALIS | B3748: =F3748&J3748&I3748 -> 5296689IOGURTESLACTALIS | C3748: #N/A | D3748: #N/A | E3748: #N/A | F3748: 5296689 | G3748: Não Atribuído | H3748: NA | I3748: LACTALIS | J3748: IOGURTES | K3748: 0 | L3748: 0 | M3748: 0 | N3748: 0 | O3748: 0 | P3748: 0 | Q3748: 0 | R3748: 0 | S3748: 0 | T3748: 0 | U3748: 0 | V3748: =VLOOKUP(A3748,Planilha1!B:E,4,0) -> 3.0503168
A3749: =J3749&I3749 -> IOGURTESLACTALIS | B3749: =F3749&J3749&I3749 -> 5363625IOGURTESLACTALIS | C3749: #N/A | D3749: #N/A | E3749: #N/A | F3749: 5363625 | G3749: Não Atribuído | H3749: NA | I3749: LACTALIS | J3749: IOGURTES | K3749: 0 | L3749: 0 | M3749: 0 | N3749: 0 | O3749: 0 | P3749: 0 | Q3749: 0 | R3749: 0 | S3749: 0 | T3749: 0 | U3749: 0 | V3749: =VLOOKUP(A3749,Planilha1!B:E,4,0) -> 3.0503168
A3750: =J3750&I3750 -> LEITE EM PÓLACTALIS | B3750: =F3750&J3750&I3750 -> 5363625LEITE EM PÓLACTALIS | C3750: #N/A | D3750: #N/A | E3750: #N/A | F3750: 5363625 | G3750: Não Atribuído | H3750: NA | I3750: LACTALIS | J3750: LEITE EM PÓ | K3750: 0 | L3750: 0 | M3750: 0 | N3750: 0 | O3750: 0 | P3750: 0 | Q3750: 0 | R3750: 0 | S3750: 0 | T3750: 0 | U3750: 0 | V3750: =VLOOKUP(A3750,Planilha1!B:E,4,0) -> -2.8055507
A3751: =J3751&I3751 -> LEITE UHTLACTALIS | B3751: =F3751&J3751&I3751 -> 5058881LEITE UHTLACTALIS | C3751: PEDRO | D3751: AMANDA | E3751: NUTRI | F3751: 5058881 | G3751: GR SERVICOS E ALIMENTACAO LTDA | H3751: SP | I3751: LACTALIS | J3751: LEITE UHT | K3751: 0 | L3751: 0 | M3751: 0 | N3751: 0 | O3751: 0 | P3751: 0 | Q3751: 720 | R3751: 0 | S3751: 0 | T3751: 0 | U3751: 0 | V3751: =VLOOKUP(A3751,Planilha1!B:E,4,0) -> 0.37177548
A3752: =J3752&I3752 -> LEITE UHTLACTALIS | B3752: =F3752&J3752&I3752 -> 5262254LEITE UHTLACTALIS | C3752: #N/A | D3752: #N/A | E3752: #N/A | F3752: 5262254 | G3752: Não Atribuído | H3752: NA | I3752: LACTALIS | J3752: LEITE UHT | K3752: 0 | L3752: 0 | M3752: 0 | N3752: 0 | O3752: 0 | P3752: 0 | Q3752: 0 | R3752: 0 | S3752: 0 | T3752: 0 | U3752: 0 | V3752: =VLOOKUP(A3752,Planilha1!B:E,4,0) -> 0.37177548
A3753: =J3753&I3753 -> LEITE UHTLACTALIS | B3753: =F3753&J3753&I3753 -> 5296689LEITE UHTLACTALIS | C3753: #N/A | D3753: #N/A | E3753: #N/A | F3753: 5296689 | G3753: Não Atribuído | H3753: NA | I3753: LACTALIS | J3753: LEITE UHT | K3753: 0 | L3753: 0 | M3753: 0 | N3753: 0 | O3753: 0 | P3753: 0 | Q3753: 0 | R3753: 0 | S3753: 0 | T3753: 0 | U3753: 0 | V3753: =VLOOKUP(A3753,Planilha1!B:E,4,0) -> 0.37177548
A3754: =J3754&I3754 -> LEITE UHTLACTALIS | B3754: =F3754&J3754&I3754 -> 5352967LEITE UHTLACTALIS | C3754: #N/A | D3754: #N/A | E3754: #N/A | F3754: 5352967 | G3754: Não Atribuído | H3754: NA | I3754: LACTALIS | J3754: LEITE UHT | K3754: 0 | L3754: 0 | M3754: 0 | N3754: 0 | O3754: 0 | P3754: 0 | Q3754: 60 | R3754: 0 | S3754: 0 | T3754: 0 | U3754: 0 | V3754: =VLOOKUP(A3754,Planilha1!B:E,4,0) -> 0.37177548
A3755: =J3755&I3755 -> CREME UHTITAMBÉ | B3755: =F3755&J3755&I3755 -> 5161583CREME UHTITAMBÉ | C3755: MAURICIO | D3755: JOEL | E3755: HENRIQUE FERREIRA | F3755: 5161583 | G3755: DOHLER AMERICA LATINA LTDA | H3755: SP | I3755: ITAMBÉ | J3755: CREME UHT | K3755: 0 | L3755: 666.6 | M3755: 264.62 | N3755: 380 | O3755: 35.9986 | P3755: 0 | Q3755: 0 | R3755: 0 | S3755: 0 | T3755: 0 | U3755: 0 | V3755: =VLOOKUP(A3755,Planilha1!B:E,4,0) -> 1.236254
A3756: =J3756&I3756 -> LPD 25KGITAMBÉ | B3756: =F3756&J3756&I3756 -> 5162170LPD 25KGITAMBÉ | C3756: MAURICIO | D3756: JOEL | E3756: JOEL ELEOTÉRIO | F3756: 5162170 | G3756: DAN VIGOR IND E COM DE LATICINIOS L | H3756: SP | I3756: ITAMBÉ | J3756: LPD 25KG | K3756: 0 | L3756: 0 | M3756: 45833.333 | N3756: 66666.667 | O3756: 0 | P3756: 0 | Q3756: 225000 | R3756: 0 | S3756: 0 | T3756: 225000 | U3756: 0 | V3756: =VLOOKUP(A3756,Planilha1!B:E,4,0) -> 3.3372177
A3757: =J3757&I3757 -> LPI 25KGITAMBÉ | B3757: =F3757&J3757&I3757 -> 5162170LPI 25KGITAMBÉ | C3757: MAURICIO | D3757: JOEL | E3757: JOEL ELEOTÉRIO | F3757: 5162170 | G3757: DAN VIGOR IND E COM DE LATICINIOS L | H3757: SP | I3757: ITAMBÉ | J3757: LPI 25KG | K3757: 0 | L3757: 0 | M3757: 95666.667 | N3757: 174666.67 | O3757: 0 | P3757: 0 | Q3757: 100000 | R3757: 0 | S3757: 0 | T3757: 100000 | U3757: 0 | V3757: =VLOOKUP(A3757,Planilha1!B:E,4,0) -> -1.2181928
A3758: =J3758&I3758 -> COMPOSTOITAMBÉ | B3758: =F3758&J3758&I3758 -> 5168003COMPOSTOITAMBÉ | C3758: MAURICIO | D3758: JOEL | E3758: JOEL | F3758: 5168003 | G3758: DAMAIS GELATUS F DE SORVETES E D LT | H3758: BA | I3758: ITAMBÉ | J3758: COMPOSTO | K3758: 0 | L3758: 0 | M3758: 0 | N3758: 0 | O3758: 0 | P3758: 0 | Q3758: 0 | R3758: 0 | S3758: 0 | T3758: 0 | U3758: 0 | V3758: =VLOOKUP(A3758,Planilha1!B:E,4,0) -> 0.15618218
A3759: =J3759&I3759 -> LPD 25KGLACTALIS | B3759: =F3759&J3759&I3759 -> 5170056LPD 25KGLACTALIS | C3759: MAURICIO | D3759: MARCELO | E3759: MARCELO RODRIGUES | F3759: 5170056 | G3759: ANTONIO ROBERTO M DOS SANTOS ME | H3759: SP | I3759: LACTALIS | J3759: LPD 25KG | K3759: 0 | L3759: -125 | M3759: 41.666667 | N3759: 0 | O3759: 20.081202 | P3759: 0 | Q3759: 0 | R3759: 0 | S3759: 0 | T3759: 0 | U3759: 0 | V3759: =VLOOKUP(A3759,Planilha1!B:E,4,0) -> 5.8936291
A3760: =J3760&I3760 -> LPI 25KGLACTALIS | B3760: =F3760&J3760&I3760 -> 5170056LPI 25KGLACTALIS | C3760: MAURICIO | D3760: MARCELO | E3760: MARCELO RODRIGUES | F3760: 5170056 | G3760: ANTONIO ROBERTO M DOS SANTOS ME | H3760: SP | I3760: LACTALIS | J3760: LPI 25KG | K3760: 0 | L3760: 250 | M3760: 166.66667 | N3760: 125 | O3760: 127.67461 | P3760: 0 | Q3760: 0 | R3760: 0 | S3760: 0 | T3760: 0 | U3760: 0 | V3760: =VLOOKUP(A3760,Planilha1!B:E,4,0) -> -4.3046759
A3761: =J3761&I3761 -> MANTEIGA 5KGLACTALIS | B3761: =F3761&J3761&I3761 -> 5171400MANTEIGA 5KGLACTALIS | C3761: MAURICIO | D3761: JOEL | E3761: HENRIQUE FERREIRA | F3761: 5171400 | G3761: PANIBRASIL MASSAS CONGELADAS LT | H3761: SP | I3761: LACTALIS | J3761: MANTEIGA 5KG | K3761: 0 | L3761: 5000 | M3761: 3293.3333 | N3761: 3633.3333 | O3761: 477.2096 | P3761: 0 | Q3761: 2500 | R3761: 0 | S3761: 0 | T3761: 2500 | U3761: 0 | V3761: =VLOOKUP(A3761,Planilha1!B:E,4,0) -> 11.476197
A3762: =J3762&I3762 -> IOGURTESLACTALIS | B3762: =F3762&J3762&I3762 -> 5171625IOGURTESLACTALIS | C3762: MAURICIO | D3762: MAURICIO | E3762: MAURICIO GALLI | F3762: 5171625 | G3762: RFG COMERCIO TRANSPORTES E SERVICOS | H3762: SP | I3762: LACTALIS | J3762: IOGURTES | K3762: 0 | L3762: 51275.52 | M3762: 47180.16 | N3762: 44161.92 | O3762: 52877 | P3762: 0 | Q3762: 55365.12 | R3762: 0 | S3762: 0 | T3762: 13063.68 | U3762: 0 | V3762: =VLOOKUP(A3762,Planilha1!B:E,4,0) -> 3.0503168
A3763: =J3763&I3763 -> SORVETESLACTALIS | B3763: =F3763&J3763&I3763 -> 5171625SORVETESLACTALIS | C3763: MAURICIO | D3763: MAURICIO | E3763: MAURICIO GALLI | F3763: 5171625 | G3763: RFG COMERCIO TRANSPORTES E SERVICOS | H3763: SP | I3763: LACTALIS | J3763: SORVETES | K3763: 0 | L3763: 1302400 | M3763: 835066.67 | N3763: 826400 | O3763: 0 | P3763: 0 | Q3763: 581600 | R3763: 0 | S3763: 0 | T3763: 173897.6 | U3763: 0 | V3763: =VLOOKUP(A3763,Planilha1!B:E,4,0) -> 0.9624044
A3764: =J3764&I3764 -> LPI 25KGITAMBÉ | B3764: =F3764&J3764&I3764 -> 5173434LPI 25KGITAMBÉ | C3764: MAURICIO | D3764: JOEL | E3764: HENRIQUE FERREIRA | F3764: 5173434 | G3764: ARACAGY SORVETES LTDA ME | H3764: MG | I3764: ITAMBÉ | J3764: LPI 25KG | K3764: 0 | L3764: 975 | M3764: 1029.1667 | N3764: 1016.6667 | O3764: 3783.4342 | P3764: 0 | Q3764: 100 | R3764: 0 | S3764: 0 | T3764: 1000 | U3764: 0 | V3764: =VLOOKUP(A3764,Planilha1!B:E,4,0) -> -1.2181928
A3765: =J3765&I3765 -> LPI 25KGLACTALIS | B3765: =F3765&J3765&I3765 -> 5173775LPI 25KGLACTALIS | C3765: MAURICIO | D3765: MARCELO | E3765: MARCELO RODRIGUES | F3765: 5173775 | G3765: N ZEPPONE E CIA LTDA | H3765: PR | I3765: LACTALIS | J3765: LPI 25KG | K3765: 0 | L3765: 10000 | M3765: 0 | N3765: 0 | O3765: 0 | P3765: 0 | Q3765: 0 | R3765: 0 | S3765: 0 | T3765: 0 | U3765: 0 | V3765: =VLOOKUP(A3765,Planilha1!B:E,4,0) -> -4.3046759
A3766: =J3766&I3766 -> COMPOSTOITAMBÉ | B3766: =F3766&J3766&I3766 -> 5174699COMPOSTOITAMBÉ | C3766: MAURICIO | D3766: MARCELO | E3766: DUAS RODAS | F3766: 5174699 | G3766: SORVETERIA AVENIDA LTDA | H3766: PR | I3766: ITAMBÉ | J3766: COMPOSTO | K3766: 0 | L3766: 5000 | M3766: 2175 | N3766: 1783.3333 | O3766: 0 | P3766: 0 | Q3766: 0 | R3766: 0 | S3766: 0 | T3766: 5000 | U3766: 0 | V3766: =VLOOKUP(A3766,Planilha1!B:E,4,0) -> 0.15618218
... A3773: =J3773&I3773 -> LPI 25KGITAMBÉ | B3773: =F3773&J3773&I3773 -> 5190033LPI 25KGITAMBÉ | C3773: MAURICIO | D3773: JOEL | E3773: HENRIQUE FERREIRA | F3773: 5190033 | G3773: MISTER SHAKE COM SORVETES E EQU | H3773: MG | I3773: ITAMBÉ | J3773: LPI 25KG | K3773: 0 | L3773: 1000 | M3773: 166.66667 | N3773: 0 | O3773: 0 | P3773: 0 | Q3773: 0 | R3773: 0 | S3773: 0 | T3773: 0 | U3773: 0 | V3773: =VLOOKUP(A3773,Planilha1!B:E,4,0) -> -1.2181928
A3774: =J3774&I3774 -> LPI 25KGLACTALIS | B3774: =F3774&J3774&I3774 -> (vazio)LPI 25KGLACTALIS | C3774: MAURICIO | D3774: TATIANA | E3774: TATI | F3774: (vazio) | G3774: LEITESOL | H3774: #N/D | I3774: LACTALIS | J3774: LPI 25KG | K3774: 0 | L3774: 0 | M3774: 0 | N3774: 0 | O3774: 0 | P3774: 0 | Q3774: 0 | R3774: 0 | S3774: 0 | T3774: 0 | U3774: 0 | V3774: =VLOOKUP(A3774,Planilha1!B:E,4,0) -> -4.3046759
A3775: =J3775&I3775 -> BLISTERITAMBÉ | B3775: =F3775&J3775&I3775 -> 5012641BLISTERITAMBÉ | C3775: =VLOOKUP(F3775,'[1]DEPARA FOOD'!$B:$M,11,0) -> RODRIGO | D3775: ALEXANDRO | E3775: GUILHERME NASCIMENTO | F3775: 5012641 | G3775: Não Atribuído | H3775: NA | I3775: ITAMBÉ | J3775: BLISTER | K3775: 0 | L3775: 0 | M3775: 0 | N3775: 0 | O3775: 0 | P3775: 0 | Q3775: 0 | R3775: 0 | S3775: 0 | T3775: 0 | U3775: 0 | V3775: =VLOOKUP(A3775,Planilha1!B:E,4,0) -> 10.339883
A3776: =J3776&I3776 -> BLISTERITAMBÉ | B3776: =F3776&J3776&I3776 -> 5014500BLISTERITAMBÉ | C3776: =VLOOKUP(F3776,'[1]DEPARA FOOD'!$B:$M,11,0) -> RODRIGO | D3776: VAGO SUL | E3776: ANTÔNIO SOUZA | F3776: 5014500 | G3776: DAVIPAN DIST GENEROS ALIM LTDA | H3776: PR | I3776: ITAMBÉ | J3776: BLISTER | K3776: 0 | L3776: 0 | M3776: 0 | N3776: 0 | O3776: 0 | P3776: 0 | Q3776: 0 | R3776: 0 | S3776: 0 | T3776: 0 | U3776: 0 | V3776: =VLOOKUP(A3776,Planilha1!B:E,4,0) -> 10.339883
A3777: =J3777&I3777 -> BLISTERITAMBÉ | B3777: =F3777&J3777&I3777 -> 5019640BLISTERITAMBÉ | C3777: =VLOOKUP(F3777,'[1]DEPARA FOOD'!$B:$M,11,0) -> MAURICIO | D3777: JOEL | E3777: HENRIQUE FERREIRA | F3777: 5019640 | G3777: Não Atribuído | H3777: NA | I3777: ITAMBÉ | J3777: BLISTER | K3777: 0 | L3777: 0 | M3777: 0 | N3777: 0 | O3777: 0 | P3777: 0 | Q3777: 0 | R3777: 0 | S3777: 0 | T3777: 0 | U3777: 0 | V3777: =VLOOKUP(A3777,Planilha1!B:E,4,0) -> 10.339883
A3778: =J3778&I3778 -> BLISTERITAMBÉ | B3778: =F3778&J3778&I3778 -> 5023997BLISTERITAMBÉ | C3778: =VLOOKUP(F3778,'[1]DEPARA FOOD'!$B:$M,11,0) -> RODRIGO | D3778: CELIO MARTINS | E3778: MARCELO SILVA | F3778: 5023997 | G3778: TOP CESTA DE ALIMENTOS LTDA | H3778: MG | I3778: ITAMBÉ | J3778: BLISTER | K3778: 0 | L3778: 0 | M3778: 0 | N3778: 0 | O3778: 0 | P3778: 0 | Q3778: 0 | R3778: 0 | S3778: 0 | T3778: 0 | U3778: 0 | V3778: =VLOOKUP(A3778,Planilha1!B:E,4,0) -> 10.339883
A3779: =J3779&I3779 -> BLISTERITAMBÉ | B3779: =F3779&J3779&I3779 -> 5083008BLISTERITAMBÉ | C3779: =VLOOKUP(F3779,'[1]DEPARA FOOD'!$B:$M,11,0) -> RODRIGO | D3779: VAGO SP - INTERIOR | E3779: EMMANUEL FRANCISCO | F3779: 5083008 | G3779: ADRIPAN PRODUTOS PARA PANIFICACAO L | H3779: SP | I3779: ITAMBÉ | J3779: BLISTER | K3779: 0 | L3779: 0 | M3779: 0 | N3779: 0 | O3779: 0 | P3779: 0 | Q3779: 0 | R3779: 0 | S3779: 0 | T3779: 0 | U3779: 0 | V3779: =VLOOKUP(A3779,Planilha1!B:E,4,0) -> 10.339883
A3780: =J3780&I3780 -> BLISTERITAMBÉ | B3780: =F3780&J3780&I3780 -> 5115191BLISTERITAMBÉ | C3780: =VLOOKUP(F3780,'[1]DEPARA FOOD'!$B:$M,11,0) -> RODRIGO | D3780: VAGO SUL | E3780: ANTÔNIO SOUZA | F3780: 5115191 | G3780: J C CASAROTTO MORO E CIA LTDA | H3780: PR | I3780: ITAMBÉ | J3780: BLISTER | K3780: 0 | L3780: 0 | M3780: 0 | N3780: 0 | O3780: 0 | P3780: 0 | Q3780: 0 | R3780: 0 | S3780: 0 | T3780: 0 | U3780: 0 | V3780: =VLOOKUP(A3780,Planilha1!B:E,4,0) -> 10.339883
A3781: =J3781&I3781 -> BLISTERITAMBÉ | B3781: =F3781&J3781&I3781 -> 5127549BLISTERITAMBÉ | C3781: =VLOOKUP(F3781,'[1]DEPARA FOOD'!$B:$M,11,0) -> MAURICIO | D3781: JOEL | E3781: HENRIQUE FERREIRA | F3781: 5127549 | G3781: Não Atribuído | H3781: NA | I3781: ITAMBÉ | J3781: BLISTER | K3781: 0 | L3781: 0 | M3781: 0 | N3781: 0 | O3781: 0 | P3781: 0 | Q3781: 0 | R3781: 0 | S3781: 0 | T3781: 0 | U3781: 0 | V3781: =VLOOKUP(A3781,Planilha1!B:E,4,0) -> 10.339883
A3782: =J3782&I3782 -> BLISTERITAMBÉ | B3782: =F3782&J3782&I3782 -> 5138371BLISTERITAMBÉ | C3782: =VLOOKUP(F3782,'[1]DEPARA FOOD'!$B:$M,11,0) -> PEDRO | D3782: AMANDA | E3782: AMANDA CARVALHO | F3782: 5138371 | G3782: MADERO INDUSTRIA E COMERCIO SA | H3782: PR | I3782: ITAMBÉ | J3782: BLISTER | K3782: 0 | L3782: 0 | M3782: 0 | N3782: 0 | O3782: 0 | P3782: 0 | Q3782: 0 | R3782: 0 | S3782: 0 | T3782: 0 | U3782: 0 | V3782: =VLOOKUP(A3782,Planilha1!B:E,4,0) -> 10.339883
A3783: =J3783&I3783 -> BLISTERITAMBÉ | B3783: =F3783&J3783&I3783 -> 5149985BLISTERITAMBÉ | C3783: =VLOOKUP(F3783,'[1]DEPARA FOOD'!$B:$M,11,0) -> RODRIGO | D3783: ALEXANDRO | E3783: GUILHERME NASCIMENTO | F3783: 5149985 | G3783: AROUMAR DISTRIB DE PRODUTOS ALIM LT | H3783: SP | I3783: ITAMBÉ | J3783: BLISTER | K3783: 0 | L3783: 0 | M3783: 0 | N3783: 0 | O3783: 0 | P3783: 0 | Q3783: 0 | R3783: 0 | S3783: 0 | T3783: 0 | U3783: 0 | V3783: =VLOOKUP(A3783,Planilha1!B:E,4,0) -> 10.339883
A3784: =J3784&I3784 -> BLISTERITAMBÉ | B3784: =F3784&J3784&I3784 -> 5151763BLISTERITAMBÉ | C3784: =VLOOKUP(F3784,'[1]DEPARA FOOD'!$B:$M,11,0) -> RODRIGO | D3784: CELIO MARTINS | E3784: MARCELO SILVA | F3784: 5151763 | G3784: INTEGRA PRODUTOS PARA PANIF LTD | H3784: MG | I3784: ITAMBÉ | J3784: BLISTER | K3784: 0 | L3784: 0 | M3784: 0 | N3784: 0 | O3784: 0 | P3784: 0 | Q3784: 0 | R3784: 0 | S3784: 0 | T3784: 0 | U3784: 0 | V3784: =VLOOKUP(A3784,Planilha1!B:E,4,0) -> 10.339883
A3785: =J3785&I3785 -> BLISTERITAMBÉ | B3785: =F3785&J3785&I3785 -> 5183495BLISTERITAMBÉ | C3785: =VLOOKUP(F3785,'[1]DEPARA FOOD'!$B:$M,11,0) -> MAURICIO | D3785: JOEL | E3785: HENRIQUE FERREIRA | F3785: 5183495 | G3785: ASTRON INDUSTRIA DE DOCES L | H3785: MG | I3785: ITAMBÉ | J3785: BLISTER | K3785: 0 | L3785: 0 | M3785: 0 | N3785: 0 | O3785: 0 | P3785: 0 | Q3785: 0 | R3785: 0 | S3785: 0 | T3785: 0 | U3785: 0 | V3785: =VLOOKUP(A3785,Planilha1!B:E,4,0) -> 10.339883
A3786: =J3786&I3786 -> BLISTERITAMBÉ | B3786: =F3786&J3786&I3786 -> 5192822BLISTERITAMBÉ | C3786: =VLOOKUP(F3786,'[1]DEPARA FOOD'!$B:$M,11,0) -> RODRIGO | D3786: RAQUEL BARBOSA | E3786: LUCAS ANDRADE | F3786: 5192822 | G3786: T T F ALIMENTOS SOROCABA LTDA | H3786: SP | I3786: ITAMBÉ | J3786: BLISTER | K3786: 0 | L3786: 0 | M3786: 0 | N3786: 0 | O3786: 0 | P3786: 0 | Q3786: 0 | R3786: 0 | S3786: 0 | T3786: 0 | U3786: 0 | V3786: =VLOOKUP(A3786,Planilha1!B:E,4,0) -> 10.339883
... A3974: =J3974&I3974 -> SPREADSITAMBÉ | B3974: =F3974&J3974&I3974 -> 5226985SPREADSITAMBÉ | C3974: =VLOOKUP(F3974,'[1]DEPARA FOOD'!$B:$M,11,0) -> RODRIGO | D3974: RAQUEL BARBOSA | E3974: RAQUEL BARBOSA | F3974: 5226985 | G3974: Não Atribuído | H3974: NA | I3974: ITAMBÉ | J3974: SPREADS | K3974: 0 | L3974: 0 | M3974: 0 | N3974: 0 | O3974: 0 | P3974: 178 | Q3974: 0 | R3974: 0 | S3974: 0 | T3974: 0 | U3974: 0 | V3974: =VLOOKUP(A3974,Planilha1!B:E,4,0) -> 9.2962611
A3975: =J3975&I3975 -> BLISTERLACTALIS | B3975: =F3975&J3975&I3975 -> 5356134BLISTERLACTALIS | C3975: #N/A | D3975: #N/A | E3975: #N/A | F3975: 5356134 | G3975: Não Atribuído | H3975: NA | I3975: LACTALIS | J3975: BLISTER | K3975: 0 | L3975: 0 | M3975: 0 | N3975: 0 | O3975: 0 | P3975: 0 | Q3975: 0 | R3975: 0 | S3975: 4 | T3975: 4 | U3975: 0 | V3975: =VLOOKUP(A3975,Planilha1!B:E,4,0) -> 13.783872
A3976: =J3976&I3976 -> IOGURTESLACTALIS | B3976: =F3976&J3976&I3976 -> 5109334IOGURTESLACTALIS | C3976: MAURICIO | D3976: TATIANA NITTA | E3976: DUAS RODAS | F3976: 5109334 | G3976: CENTRAL OSASCO DIST ALIM E BEBI | H3976: SP | I3976: LACTALIS | J3976: IOGURTES | K3976: 0 | L3976: 0 | M3976: 0 | N3976: 0 | O3976: 0 | P3976: 0 | Q3976: 0 | R3976: 0 | S3976: 0 | T3976: 0 | U3976: 0 | V3976: =VLOOKUP(A3976,Planilha1!B:E,4,0) -> 3.0503168
A3977: =J3977&I3977 -> IOGURTESLACTALIS | B3977: =F3977&J3977&I3977 -> 5261001IOGURTESLACTALIS | C3977: #N/A | D3977: #N/A | E3977: #N/A | F3977: 5261001 | G3977: Não Atribuído | H3977: NA | I3977: LACTALIS | J3977: IOGURTES | K3977: 0 | L3977: 0 | M3977: 0 | N3977: 0 | O3977: 0 | P3977: 0 | Q3977: 0 | R3977: 0 | S3977: 0 | T3977: 0 | U3977: 0 | V3977: =VLOOKUP(A3977,Planilha1!B:E,4,0) -> 3.0503168
A3978: =J3978&I3978 -> LEITE CONDENSADOLACTALIS | B3978: =F3978&J3978&I3978 -> 5261001LEITE CONDENSADOLACTALIS | C3978: #N/A | D3978: #N/A | E3978: #N/A | F3978: 5261001 | G3978: Não Atribuído | H3978: NA | I3978: LACTALIS | J3978: LEITE CONDENSADO | K3978: 0 | L3978: 0 | M3978: 0 | N3978: 0 | O3978: 0 | P3978: 0 | Q3978: 0 | R3978: 0 | S3978: 9 | T3978: 9 | U3978: 9 | V3978: =VLOOKUP(A3978,Planilha1!B:E,4,0) -> 1.8665072
A3979: =J3979&I3979 -> LEITE UHTLACTALIS | B3979: =F3979&J3979&I3979 -> 5261001LEITE UHTLACTALIS | C3979: #N/A | D3979: #N/A | E3979: #N/A | F3979: 5261001 | G3979: Não Atribuído | H3979: NA | I3979: LACTALIS | J3979: LEITE UHT | K3979: 0 | L3979: 0 | M3979: 0 | N3979: 0 | O3979: 0 | P3979: 0 | Q3979: 0 | R3979: 0 | S3979: 0 | T3979: 0 | U3979: 0 | V3979: =VLOOKUP(A3979,Planilha1!B:E,4,0) -> 0.37177548
A3980: =J3980&I3980 -> LEITE UHTLACTALIS | B3980: =F3980&J3980&I3980 -> 5356134LEITE UHTLACTALIS | C3980: #N/A | D3980: #N/A | E3980: #N/A | F3980: 5356134 | G3980: Não Atribuído | H3980: NA | I3980: LACTALIS | J3980: LEITE UHT | K3980: 0 | L3980: 0 | M3980: 0 | N3980: 0 | O3980: 0 | P3980: 0 | Q3980: 0 | R3980: 0 | S3980: 0 | T3980: 0 | U3980: 0 | V3980: =VLOOKUP(A3980,Planilha1!B:E,4,0) -> 0.37177548
A3981: =J3981&I3981 -> MANTEIGA 5KGITAMBÉ | B3981: =F3981&J3981&I3981 -> 5002549MANTEIGA 5KGITAMBÉ | C3981: PEDRO | D3981: ANA MENIQUETE | E3981: ANA MENIQUETE | F3981: 5002549 | G3981: SERVCATER INTERNACIONAL LTDA | H3981: SP | I3981: ITAMBÉ | J3981: MANTEIGA 5KG | K3981: 0 | L3981: 0 | M3981: 0 | N3981: 0 | O3981: 0 | P3981: 0 | Q3981: 0 | R3981: 0 | S3981: 300 | T3981: 300 | U3981: 200 | V3981: =VLOOKUP(A3981,Planilha1!B:E,4,0) -> 5.8198005
A3982: =J3982&I3982 -> MANTEIGA 5KGITAMBÉ | B3982: =F3982&J3982&I3982 -> 5041289MANTEIGA 5KGITAMBÉ | C3982: PEDRO | D3982: AMANDA | E3982: AMANDA CARVALHO | F3982: 5041289 | G3982: C B BRASILIA COM DE ALIMENTOS LTDA | H3982: DF | I3982: ITAMBÉ | J3982: MANTEIGA 5KG | K3982: 0 | L3982: 0 | M3982: 0 | N3982: 0 | O3982: 0 | P3982: 0 | Q3982: 0 | R3982: 0 | S3982: 0 | T3982: 3500 | U3982: 50 | V3982: =VLOOKUP(A3982,Planilha1!B:E,4,0) -> 5.8198005
A3983: =J3983&I3983 -> MANTEIGA 5KGITAMBÉ | B3983: =F3983&J3983&I3983 -> 5181144MANTEIGA 5KGITAMBÉ | C3983: MAURICIO | D3983: TATIANA NITTA | E3983: TATIANA NITTA | F3983: 5181144 | G3983: INDUSTRIA DE SORVETES CAMAGIVA LTDA | H3983: SP | I3983: ITAMBÉ | J3983: MANTEIGA 5KG | K3983: 0 | L3983: 0 | M3983: 0 | N3983: 0 | O3983: 0 | P3983: 0 | Q3983: 0 | R3983: 0 | S3983: 0 | T3983: 0 | U3983: 0 | V3983: =VLOOKUP(A3983,Planilha1!B:E,4,0) -> 5.8198005
A3984: =J3984&I3984 -> MANTEIGA 5KGITAMBÉ | B3984: =F3984&J3984&I3984 -> 5223622MANTEIGA 5KGITAMBÉ | C3984: PEDRO | D3984: AMANDA | E3984: AMANDA CARVALHO | F3984: 5223622 | G3984: CBX CG COMERCIO DE ALIMENTOS LT | H3984: MS | I3984: ITAMBÉ | J3984: MANTEIGA 5KG | K3984: 0 | L3984: 0 | M3984: 0 | N3984: 0 | O3984: 0 | P3984: 0 | Q3984: 70 | R3984: 0 | S3984: 0 | T3984: 0 | U3984: 70 | V3984: =VLOOKUP(A3984,Planilha1!B:E,4,0) -> 5.8198005
A3985: =J3985&I3985 -> MANTEIGA 5KGITAMBÉ | B3985: =F3985&J3985&I3985 -> 5233833MANTEIGA 5KGITAMBÉ | C3985: #N/A | D3985: #N/A | E3985: #N/A | F3985: 5233833 | G3985: Não Atribuído | H3985: NA | I3985: ITAMBÉ | J3985: MANTEIGA 5KG | K3985: 0 | L3985: 0 | M3985: 0 | N3985: 0 | O3985: 0 | P3985: 0 | Q3985: 0 | R3985: 0 | S3985: 0 | T3985: 0 | U3985: 50 | V3985: =VLOOKUP(A3985,Planilha1!B:E,4,0) -> 5.8198005
A3986: =J3986&I3986 -> MANTEIGA 5KGITAMBÉ | B3986: =F3986&J3986&I3986 -> 5315925MANTEIGA 5KGITAMBÉ | C3986: PEDRO | D3986: AMANDA | E3986: AMANDA CARVALHO | F3986: 5315925 | G3986: CB VITORIA COMERCIO DE ALIMENTO | H3986: ES | I3986: ITAMBÉ | J3986: MANTEIGA 5KG | K3986: 0 | L3986: 0 | M3986: 0 | N3986: 0 | O3986: 0 | P3986: 0 | Q3986: 0 | R3986: 0 | S3986: 0 | T3986: 0 | U3986: 160 | V3986: =VLOOKUP(A3986,Planilha1!B:E,4,0) -> 5.8198005
A3987: =J3987&I3987 -> MANTEIGA 5KGITAMBÉ | B3987: =F3987&J3987&I3987 -> 5332394MANTEIGA 5KGITAMBÉ | C3987: #N/A | D3987: #N/A | E3987: #N/A | F3987: 5332394 | G3987: Não Atribuído | H3987: NA | I3987: ITAMBÉ | J3987: MANTEIGA 5KG | K3987: 0 | L3987: 0 | M3987: 0 | N3987: 0 | O3987: 0 | P3987: 0 | Q3987: 0 | R3987: 0 | S3987: 0 | T3987: 0 | U3987: 50 | V3987: =VLOOKUP(A3987,Planilha1!B:E,4,0) -> 5.8198005
A3988: =J3988&I3988 -> MANTEIGA 5KGITAMBÉ | B3988: =F3988&J3988&I3988 -> 5350655MANTEIGA 5KGITAMBÉ | C3988: PEDRO | D3988: AMANDA | E3988: AMANDA CARVALHO | F3988: 5350655 | G3988: CB CAMPINAS COM DE ALIMEN LTDA | H3988: SP | I3988: ITAMBÉ | J3988: MANTEIGA 5KG | K3988: 0 | L3988: 0 | M3988: 0 | N3988: 0 | O3988: 0 | P3988: 0 | Q3988: 50 | R3988: 0 | S3988: 0 | T3988: 0 | U3988: 0 | V3988: =VLOOKUP(A3988,Planilha1!B:E,4,0) -> 5.8198005
A3989: =J3989&I3989 -> MANTEIGA 5KGITAMBÉ | B3989: =F3989&J3989&I3989 -> 5350677MANTEIGA 5KGITAMBÉ | C3989: PEDRO | D3989: AMANDA | E3989: AMANDA CARVALHO | F3989: 5350677 | G3989: CB GUARULHOS COMER DE ALIMEN LT | H3989: SP | I3989: ITAMBÉ | J3989: MANTEIGA 5KG | K3989: 0 | L3989: 0 | M3989: 0 | N3989: 0 | O3989: 0 | P3989: 0 | Q3989: 0 | R3989: 0 | S3989: 0 | T3989: 0 | U3989: 80 | V3989: =VLOOKUP(A3989,Planilha1!B:E,4,0) -> 5.8198005
A3990: =J3990&I3990 -> MANTEIGA 5KGITAMBÉ | B3990: =F3990&J3990&I3990 -> 5350696MANTEIGA 5KGITAMBÉ | C3990: PEDRO | D3990: AMANDA | E3990: AMANDA CARVALHO | F3990: 5350696 | G3990: CB JUNDIAI COMERCIO DE ALIMEN L | H3990: SP | I3990: ITAMBÉ | J3990: MANTEIGA 5KG | K3990: 0 | L3990: 0 | M3990: 0 | N3990: 0 | O3990: 0 | P3990: 0 | Q3990: 80 | R3990: 0 | S3990: 0 | T3990: 0 | U3990: 0 | V3990: =VLOOKUP(A3990,Planilha1!B:E,4,0) -> 5.8198005
A3991: =J3991&I3991 -> MANTEIGA 5KGITAMBÉ | B3991: =F3991&J3991&I3991 -> 5350697MANTEIGA 5KGITAMBÉ | C3991: #N/A | D3991: #N/A | E3991: #N/A | F3991: 5350697 | G3991: Não Atribuído | H3991: NA | I3991: ITAMBÉ | J3991: MANTEIGA 5KG | K3991: 0 | L3991: 0 | M3991: 0 | N3991: 0 | O3991: 0 | P3991: 0 | Q3991: 0 | R3991: 0 | S3991: 0 | T3991: 0 | U3991: 0 | V3991: =VLOOKUP(A3991,Planilha1!B:E,4,0) -> 5.8198005
A3992: =J3992&I3992 -> MANTEIGA 5KGITAMBÉ | B3992: =F3992&J3992&I3992 -> 5350699MANTEIGA 5KGITAMBÉ | C3992: PEDRO | D3992: AMANDA | E3992: AMANDA CARVALHO | F3992: 5350699 | G3992: CB OSASCO COMERCIO DE ALIMENTOS | H3992: SP | I3992: ITAMBÉ | J3992: MANTEIGA 5KG | K3992: 0 | L3992: 0 | M3992: 0 | N3992: 0 | O3992: 0 | P3992: 0 | Q3992: 0 | R3992: 0 | S3992: 0 | T3992: 0 | U3992: 0 | V3992: =VLOOKUP(A3992,Planilha1!B:E,4,0) -> 5.8198005
A3993: =J3993&I3993 -> MANTEIGA 5KGITAMBÉ | B3993: =F3993&J3993&I3993 -> 5350701MANTEIGA 5KGITAMBÉ | C3993: #N/A | D3993: #N/A | E3993: #N/A | F3993: 5350701 | G3993: Não Atribuído | H3993: NA | I3993: ITAMBÉ | J3993: MANTEIGA 5KG | K3993: 0 | L3993: 0 | M3993: 0 | N3993: 0 | O3993: 0 | P3993: 0 | Q3993: 0 | R3993: 0 | S3993: 0 | T3993: 0 | U3993: 120 | V3993: =VLOOKUP(A3993,Planilha1!B:E,4,0) -> 5.8198005
A3994: =J3994&I3994 -> MANTEIGA 5KGITAMBÉ | B3994: =F3994&J3994&I3994 -> 5350702MANTEIGA 5KGITAMBÉ | C3994: #N/A | D3994: #N/A | E3994: #N/A | F3994: 5350702 | G3994: Não Atribuído | H3994: NA | I3994: ITAMBÉ | J3994: MANTEIGA 5KG | K3994: 0 | L3994: 0 | M3994: 0 | N3994: 0 | O3994: 0 | P3994: 0 | Q3994: 80 | R3994: 0 | S3994: 0 | T3994: 0 | U3994: 0 | V3994: =VLOOKUP(A3994,Planilha1!B:E,4,0) -> 5.8198005
...

Sheet Planilha1
B2: RESUMO FORECAST SEMANAL - JAN/26
B3: =D3&C3 -> BLISTERLACTALIS | C3: LACTALIS | D3: BLISTER | E3: 13.783872
B4: =D4&C4 -> COMPOSTOLACTALIS | C4: LACTALIS | D4: COMPOSTO | E4: 7.7134688
B5: =D5&C5 -> CREME 35%LACTALIS | C5: LACTALIS | D5: CREME 35% | E5: 6.4420264
B6: =D6&C6 -> CREME UHTLACTALIS | C6: LACTALIS | D6: CREME UHT | E6: -1.4094523
B7: =D7&C7 -> DOCE DE LEITELACTALIS | C7: LACTALIS | D7: DOCE DE LEITE | E7: 5.6473514
B8: =D8&C8 -> IOGURTESLACTALIS | C8: LACTALIS | D8: IOGURTES | E8: 3.0503168
B9: =D9&C9 -> LEITE CONDENSADOLACTALIS | C9: LACTALIS | D9: LEITE CONDENSADO | E9: 1.8665072
B10: =D10&C10 -> LEITE EM PÓLACTALIS | C10: LACTALIS | D10: LEITE EM PÓ | E10: -2.8055507
B11: =D11&C11 -> LEITE UHTLACTALIS | C11: LACTALIS | D11: LEITE UHT | E11: 0.37177548
B12: =D12&C12 -> MERC + AROMLACTALIS | C12: LACTALIS | D12: MERC + AROM | E12: 0.86907188
B13: =D13&C13 -> PARMESÃOLACTALIS | C13: LACTALIS | D13: PARMESÃO | E13: 6.310327
B14: =D14&C14 -> QUEIJOSLACTALIS | C14: LACTALIS | D14: QUEIJOS | E14: -1.917131
... B40: =D40&C40 -> Não atribuídoITAMBÉ | C40: ITAMBÉ | D40: Não atribuído | E40: 0
